README.txt
setup.py
vec2rec/hello_vec2rec.py
vec2rec.egg-info/PKG-INFO
vec2rec.egg-info/SOURCES.txt
vec2rec.egg-info/dependency_links.txt
vec2rec.egg-info/requires.txt
vec2rec.egg-info/top_level.txt
vec2rec.egg-info/zip-safe