Metadata-Version: 1.0
Name: vec2rec
Version: 1.0.0
Summary: An embedding tools for recommend system
Home-page: http://carrychang.top
Author: carrychang
Author-email: coolcahng@gmail.com
License: MIT
Keywords: rec embedding vec ml
Platform: UNKNOWN
